gokart_pipeliner/__init__.py
gokart_pipeliner/config_manager.py
gokart_pipeliner/enum.py
gokart_pipeliner/instantiation_task.py
gokart_pipeliner/pipeliner.py
gokart_pipeliner-0.0.8.dist-info/LICENSE
gokart_pipeliner-0.0.8.dist-info/WHEEL
gokart_pipeliner-0.0.8.dist-info/METADATA
gokart_pipeliner-0.0.8.dist-info/RECORD
