Metadata-Version: 2.1
Name: gokart-pipeliner
Version: 0.0.8
Summary: gokart pipeline
Home-page: https://github.com/vaaaaanquish/gokart-pipeliner
License: MIT
Author: vaaaaanquish
Author-email: 6syun9@gmail.com
Requires-Python: >=3.6,<4.0
Classifier: License :: OSI Approved :: MIT License
Classifier: Programming Language :: Python :: 3
Classifier: Programming Language :: Python :: 3.6
Classifier: Programming Language :: Python :: 3.7
Classifier: Programming Language :: Python :: 3.8
Classifier: Programming Language :: Python :: 3.9
Requires-Dist: gokart
Project-URL: Repository, https://github.com/vaaaaanquish/gokart-pipeliner
